auto_name_enum/__init__.py
auto_name_enum/base.py
auto_name_enum/mixins.py
auto_name_enum/py.typed
auto_name_enum-3.0.0.dist-info/METADATA
auto_name_enum-3.0.0.dist-info/WHEEL
auto_name_enum-3.0.0.dist-info/licenses/LICENSE.md
auto_name_enum-3.0.0.dist-info/RECORD
