Metadata-Version: 2.4
Name: auto-name-enum
Version: 3.0.0
Summary: String-based Enum class that automatically assigns values
Author-email: Tucker Beck <tucker.beck@gmail.com>
License-File: LICENSE.md
Requires-Python: >=3.9
Requires-Dist: typing-extensions>=4.13.2; python_full_version < '3.12'
